{
	"previous_hash_4_hex": [
		"1234567890abcdef",
		"2234567890abcdef",
		"3234567890abcdef",
		"4234567890abcdef"
	],
	"update_utc_time_second": "YYYY-MM-DDThh:mm:ssTZD",
	"committee_members": ["james_wang", "Pi", "vincent"],
	"rbas_system_specification": {
		"servers_software": [
			"rs.js",
			"gs.js",
			"ts.js",
			"qs.js",
			"db.js",
			"rs_dash_board.js"
		],
		"api_json": ["rs_sync", "rs_gs", "gs_ts", "ts_db", "rs_db", "qs_db"],
		"system_admin_json": ["rs_list", "gs_list", "qs_list", "db_list"],
		"system_tester": ["hash_simulator", "ts_app", "qs_app"]
	},
	"root_servers": ["rs0", "rs1", "rs2"]
}
